videosdk/agents/__init__.py
videosdk/agents/__main__.py
videosdk/agents/agent.py
videosdk/agents/agent_session.py
videosdk/agents/background_audio.py
videosdk/agents/cascading_pipeline.py
videosdk/agents/cli.py
videosdk/agents/console_mode.py
videosdk/agents/conversation_flow.py
videosdk/agents/denoise.py
videosdk/agents/dtmf_handler.py
videosdk/agents/eou.py
videosdk/agents/event_bus.py
videosdk/agents/event_emitter.py
videosdk/agents/fallback_base.py
videosdk/agents/images.py
videosdk/agents/init_config.py
videosdk/agents/job.py
videosdk/agents/pipeline.py
videosdk/agents/playground_manager.py
videosdk/agents/realtime_base_model.py
videosdk/agents/realtime_pipeline.py
videosdk/agents/utils.py
videosdk/agents/utterance_handle.py
videosdk/agents/vad.py
videosdk/agents/version.py
videosdk/agents/voice_mail_detector.py
videosdk/agents/worker.py
videosdk/agents/a2a/card.py
videosdk/agents/a2a/protocol.py
videosdk/agents/backend/__init__.py
videosdk/agents/backend/connection.py
videosdk/agents/backend/protocol.py
videosdk/agents/debug/__init__.py
videosdk/agents/debug/dashboard.html
videosdk/agents/debug/http_server.py
videosdk/agents/debug/tracing.py
videosdk/agents/execution/__init__.py
videosdk/agents/execution/base_resource.py
videosdk/agents/execution/inference_resource.py
videosdk/agents/execution/resource_manager.py
videosdk/agents/execution/resources.py
videosdk/agents/execution/task_executor.py
videosdk/agents/execution/types.py
videosdk/agents/knowledge_base/__init__.py
videosdk/agents/knowledge_base/base.py
videosdk/agents/knowledge_base/config.py
videosdk/agents/llm/__init__.py
videosdk/agents/llm/chat_context.py
videosdk/agents/llm/fallback_llm.py
videosdk/agents/llm/llm.py
videosdk/agents/mcp/mcp_manager.py
videosdk/agents/mcp/mcp_server.py
videosdk/agents/metrics/__init__.py
videosdk/agents/metrics/analytics.py
videosdk/agents/metrics/cascading_metrics_collector.py
videosdk/agents/metrics/integration.py
videosdk/agents/metrics/logs.py
videosdk_agents-0.0.58.dist-info/METADATA
videosdk_agents-0.0.58.dist-info/WHEEL
videosdk_agents-0.0.58.dist-info/entry_points.txt
videosdk_agents-0.0.58.dist-info/RECORD
